accounting_vod/__init__.py
accounting_vod/builder.py
accounting_vod/core.py
accounting_vod/definitions.py
accounting_vod-0.1.3.dist-info/licenses/LICENSE
accounting_vod-0.1.3.dist-info/METADATA
accounting_vod-0.1.3.dist-info/WHEEL
accounting_vod-0.1.3.dist-info/top_level.txt
accounting_vod-0.1.3.dist-info/RECORD
