Metadata-Version: 2.4
Name: accounting_vod
Version: 0.1.3
Summary: Generate VOD XML export for accounting software 
Home-page: https://github.com/boris-savic/python-accounting-vod
Download-URL: https://github.com/boris-savic/python-accounting-vod/tarball/0.1.3
Author: Boris Savic
Author-email: boris70@gmail.com
Keywords: python vod,accounting,opal
License-File: LICENSE
Requires-Dist: lxml>=4.4.1
Dynamic: author
Dynamic: author-email
Dynamic: download-url
Dynamic: home-page
Dynamic: keywords
Dynamic: license-file
Dynamic: requires-dist
Dynamic: summary
